{
    "format_version": "1.20.10",
    "minecraft:recipe_shaped": {
        "description": {
            "identifier": "vmh:phantom_head"
        },
        "tags": [
            "crafting_table"
        ],
        "group": "itemGroup.name.skull",
        "pattern": [
            "#"
        ],
        "key": {
            "#": {
                "item": "vmh:phantom_head_block"
            }
        },
        "unlock": [
            {
                "item": "vmh:phantom_head_block"
            }
        ],
        "result": {
            "item": "vmh:phantom_head",
            "count": 1
        }
    }
}